lesting.thrift-0.1.0-py3.9-nspkg.pth
lesting/thrift/__init__.py
lesting/thrift/thrift.py
lesting/thrift/protocol/__init__.py
lesting/thrift/protocol/base.py
lesting/thrift/protocol/binary.py
lesting/thrift/protocol/compact.py
lesting/thrift/transport/__init__.py
lesting/thrift/transport/base.py
lesting/thrift/transport/http.py
lesting/thrift/transport/socket.py
lesting.thrift-0.1.0.dist-info/LICENSE
lesting.thrift-0.1.0.dist-info/METADATA
lesting.thrift-0.1.0.dist-info/WHEEL
lesting.thrift-0.1.0.dist-info/namespace_packages.txt
lesting.thrift-0.1.0.dist-info/top_level.txt
lesting.thrift-0.1.0.dist-info/RECORD
