Metadata-Version: 2.1
Name: lesting.thrift
Version: 0.1.0
Summary: Lesting Apache Thrift
Home-page: https://github.com/LESTINGX/THRIFT
Author: UNKNOWN
Author-email: UNKNOWN
License: UNKNOWN
Platform: UNKNOWN
Classifier: License :: OSI Approved :: MIT License
Classifier: Programming Language :: Python :: 3.5
Classifier: Programming Language :: Python :: 3.6
Classifier: Programming Language :: Python :: 3.7
Classifier: Programming Language :: Python :: 3.8
Classifier: Programming Language :: Python :: 3.9
Classifier: Programming Language :: Python :: 3.10
Classifier: Operating System :: OS Independent
Requires-Dist: thriftpy2
Requires-Dist: lesting.http
